{
  "data": {
    "offersListByPath": {
      "item": {
        "availableOffersList": [
          {
            "code": "QUICK650",
            "image": {
              "_path": "/content/dam/s6web/in/en/assets/offers1.jpg"
            },
            "title": "Mobiquick Wallet",
            "note": "Get upto ₹650 back!",
            "description": {
              "html": "<p>On bookings above&nbsp;₹3000. T&amp;C Apply <a href=\"/content/skyplus6e/in/en/home.html\" target=\"_self\">View Details</a></p>\n",
              "json": [
                {
                  "nodeType": "paragraph",
                  "content": [
                    {
                      "nodeType": "text",
                      "value": "On bookings above ₹3000. T&C Apply "
                    },
                    {
                      "nodeType": "link",
                      "data": {
                        "href": "/content/skyplus6e/in/en/home.html",
                        "target": "_self"
                      },
                      "value": "View Details"
                    }
                  ]
                }
              ]
            },
            "discountcashback": "CASHBACK"
          },
          {
            "code": "QUICK7000",
            "image": {
              "_path": "/content/dam/s6web/in/en/assets/offers2.jpg"
            },
            "title": "Mobiquick Wallet",
            "note": "Save upto ₹500!",
            "description": {
              "html": "<p>On bookings above ₹3000. T&amp;C Apply <a href=\"/content/skyplus6e/in/en/home.html\" target=\"_blank\">View Details</a></p>\n",
              "json": [
                {
                  "nodeType": "paragraph",
                  "content": [
                    {
                      "nodeType": "text",
                      "value": "On bookings above ₹3000. T&C Apply "
                    },
                    {
                      "nodeType": "link",
                      "data": {
                        "href": "/content/skyplus6e/in/en/home.html",
                        "target": "_blank"
                      },
                      "value": "View Details"
                    }
                  ]
                }
              ]
            },
            "discountcashback": "7% OFF"
          },
          {
            "code": "QUICK10",
            "image": {
              "_path": "/content/dam/s6web/in/en/assets/offers1.jpg"
            },
            "title": "Mobiquick Bank",
            "note": "Save upto ₹800!",
            "description": {
              "html": "<p>On bookings above ₹3000. T&amp;C Apply <a href=\"/content/skyplus6e/in/en/home/home.html\" target=\"_blank\">View Details</a></p>\n",
              "json": [
                {
                  "nodeType": "paragraph",
                  "content": [
                    {
                      "nodeType": "text",
                      "value": "On bookings above ₹3000. T&C Apply "
                    },
                    {
                      "nodeType": "link",
                      "data": {
                        "href": "/content/skyplus6e/in/en/home/home.html",
                        "target": "_blank"
                      },
                      "value": "View Details"
                    }
                  ]
                }
              ]
            },
            "discountcashback": "10% OFF"
          }
        ]
      }
    }
  }
}